{
  "contestSlug": "2026-0102-open",
  "contestTitle": "월간 향유회 2026. 01-02. Open Contest",
  "contestId": "1653",
  "problemIndex": 1,
  "problemNumber": "A",
  "problemTitle": "월간 향유회 시즌 종료",
  "bojProblemId": "35306",
  "infoHtml": "<thead><tr><th style=\"width:16%;\">시간 제한</th><th style=\"width:16%;\">메모리 제한</th><th style=\"width:17%;\">제출</th><th style=\"width:17%;\">정답</th><th style=\"width:17%;\">맞힌 사람</th><th style=\"width:17%;\">정답 비율</th></tr></thead><tbody><tr><td>1 초 </td><td>1024 MB</td><td>436</td><td>267</td><td>216</td><td>60.845%</td></tr></tbody>",
  "bodyHtml": "\n\t\t\t<div class=\"col-md-12\">\n\t\t\t\t<section id=\"description\"  class=\"problem-section\">\n\t\t\t\t<div class=\"headline\">\n\t\t\t\t<h2>문제</h2>\n\t\t\t\t</div>\n\t\t\t\t<div id=\"problem_description\" class=\"problem-text\">\n\t\t\t\t<p>월간 향유회 시즌 1이 종료된다. 시즌 1의 수장 pjshwa는 $N$명의 운영진 중 다음 시즌의 수장을 지목하려고 한다.</p>\r\n\r\n<p>하지만 아무에게나 수장을 맡길 수 없었던 pjshwa는 각 운영진의 능력을 파악하기 위해 $K$개의 평가 지표를 만들었다. 수장이 되기 위해서는 다른 모든 운영진보다 높은 평가 지표가 하나 이상 있어야 한다. pjshwa가 다음 시즌의 수장으로 지목할 수 있는 운영진의 수를 알아내 보자!</p>\r\n\n\t\t\t\t</div>\n\t\t\t\t</section>\n\t\t\t</div>\n\t\t\t\t\t\t\t\t\t\t<div class=\"col-md-12\">\n\t\t\t\t\t<section id=\"input\"  class=\"problem-section\">\n\t\t\t\t\t<div class=\"headline\">\n\t\t\t\t\t<h2>입력</h2>\n\t\t\t\t\t</div>\n\t\t\t\t\t<div id=\"problem_input\" class=\"problem-text\">\n\t\t\t\t\t<p>첫째 줄에 운영진의 수 $N$, 평가 지표의 수 $K$가 공백으로 구분되어 주어진다. $(1\\leq N, K \\leq 2\\,000)$</p>\r\n\r\n<p>둘째 줄부터 $N$개의 줄에 걸쳐 각 줄에 운영진의 지표를 나타내는 $K$개의 정수가 공백으로 구분되어 주어진다. $N$개의 줄 중 $i$번째 줄의 $j$번째 정수는 $i$번째 사람의 $j$번째 평가 지표를 의미한다. 각 수는 $1$ 이상 $200\\,000$이하이다.</p>\r\n\n\t\t\t\t\t</div>\n\t\t\t\t\t</section>\n\t\t\t\t</div>\n\t\n\t\t\t\t<div class=\"col-md-12\">\n\t\t\t\t\t<section id=\"output\"  class=\"problem-section\">\n\t\t\t\t\t<div class=\"headline\">\n\t\t\t\t\t<h2>출력</h2>\n\t\t\t\t\t</div>\n\t\t\t\t\t<div id=\"problem_output\" class=\"problem-text\">\n\t\t\t\t\t<p>다음 시즌의 수장으로 지목할 수 있는 운영진의 수를 출력한다.</p>\r\n\n\t\t\t\t\t</div>\n\t\t\t\t\t</section>\n\t\t\t\t</div>\n\t\t\t\t\t\t<div class=\"col-md-12\">\n\t\t\t<section id=\"limit\" style=\"display:none;\" class=\"problem-section\">\n\t\t\t<div class=\"headline\">\n\t\t\t<h2>제한</h2>\n\t\t\t</div>\n\t\t\t<div id=\"problem_limit\" class=\"problem-text\">\n\t\t\t\t\t\t</div>\n\t\t\t</section>\n\t\t\t</div>\n\t\t\t\t\t\t\t\t\t\t\t\t\t\t\t\t\t<div class=\"col-md-12\">\n\t\t\t\t<div class=\"row\">\n\t\t\t\t\t<div class=\"col-md-6\">\n\t\t\t\t\t\t<section id=\"sampleinput1\">\n\t\t\t\t\t\t<div class=\"headline\">\n\t\t\t\t\t\t<h2>예제 입력 1\n\t\t\t\t\t\t\t\n\t\t\t\t\t\t</h2>\n\t\t\t\t\t\t</div>\n\t\t\t\t\t\t<pre class=\"sampledata\" id=\"sample-input-1\">4 3\n2 3 3\n3 2 4\n3 2 2\n1 2 1\n</pre>\n\t\t\t\t\t\t</section>\n\t\t\t\t\t</div>\n\t\t\t\t\t<div class=\"col-md-6\">\n\t\t\t\t\t\t<section id=\"sampleoutput1\">\n\t\t\t\t\t\t<div class=\"headline\">\n\t\t\t\t\t\t<h2>예제 출력 1\n\t\t\t\t\t\t\t\n\t\t\t\t\t\t</h2>\n\t\t\t\t\t\t</div>\n\t\t\t\t\t\t<pre class=\"sampledata\" id=\"sample-output-1\">2\n</pre>\n\t\t\t\t\t\t</section>\n\t\t\t\t\t</div>\n\t\t\t\t\t\t\t\t\t</div>\n\t\t\t\t</div>\n\t\t\t\t\t\t\t\t<div class=\"col-md-12\">\n\t\t\t\t<div class=\"row\">\n\t\t\t\t\t<div class=\"col-md-6\">\n\t\t\t\t\t\t<section id=\"sampleinput2\">\n\t\t\t\t\t\t<div class=\"headline\">\n\t\t\t\t\t\t<h2>예제 입력 2\n\t\t\t\t\t\t\t\n\t\t\t\t\t\t</h2>\n\t\t\t\t\t\t</div>\n\t\t\t\t\t\t<pre class=\"sampledata\" id=\"sample-input-2\">1 6\n2026 2 22 16 32 14\n</pre>\n\t\t\t\t\t\t</section>\n\t\t\t\t\t</div>\n\t\t\t\t\t<div class=\"col-md-6\">\n\t\t\t\t\t\t<section id=\"sampleoutput2\">\n\t\t\t\t\t\t<div class=\"headline\">\n\t\t\t\t\t\t<h2>예제 출력 2\n\t\t\t\t\t\t\t\n\t\t\t\t\t\t</h2>\n\t\t\t\t\t\t</div>\n\t\t\t\t\t\t<pre class=\"sampledata\" id=\"sample-output-2\">1\n</pre>\n\t\t\t\t\t\t</section>\n\t\t\t\t\t</div>\n\t\t\t\t\t\t\t\t\t</div>\n\t\t\t\t</div>\n\t\t\t\t\t\t\t\t\t\t<div class=\"col-md-12\">\n\t\t\t\t<section id=\"hint\" style=\"display: none;\" class=\"problem-section\">\n\t\t\t\t<div class=\"headline\">\n\t\t\t\t<h2>노트</h2>\n\t\t\t\t</div>\n\t\t\t\t<div id=\"problem_hint\" class=\"problem-text\">\n\t\t\t\t\n\t\t\t\t</div>\n\t\t\t\t</section>\n\t\t\t</div>\n\t\t\t\t\t\t\t\t</div>\n\t\t\t\t\t\t\t\t\t<div class=\"col-md-12\"><section id=\"source\"><div class=\"headline\"><h2>출처</h2></div><p>Contest&nbsp;&gt;&nbsp;BOJ User Contest&nbsp;&gt;&nbsp;월간 향유회&nbsp;&gt;&nbsp;월간 향유회 2026. 01-02.&nbsp;A번</p><ul><li>문제를 만든 사람:&nbsp;swoon</li><li>문제를 검수한 사람:&nbsp;chogahui05, cologne, heeda0528, utilforever</li></ul></section></div>\n\t\t\t\t\t\t\t\t\t\t\t\t\t\t\t\t\t\t\t\t\t\t\t\t\t\t\t"
}
